diskpop/__init__.py
diskpop/run_set.py
diskpop/setup.py
diskpop/test.py
diskpop/diskpop/__init__.py
diskpop/diskpop/_version.py
diskpop/diskpop/analysis.py
diskpop/diskpop/analytic_disc.py
diskpop/diskpop/defaults.py
diskpop/diskpop/eos_diskpop.py
diskpop/diskpop/io_diskpop.py
diskpop/diskpop/main.py
diskpop/diskpop/observe.py
diskpop/diskpop/population.py
diskpop/diskpop/star.py
diskpop/diskpop/streamlineddisc.py
diskpop/diskpop/streamlinedstar.py
diskpop/diskpop/yso copy.py
diskpop/diskpop/yso.py
diskpop/diskpop/DiscEvolution/LICENSE
diskpop/diskpop/DiscEvolution/__init__.py
diskpop/diskpop/DiscEvolution/src/ViscousEvolution.py
diskpop/diskpop/DiscEvolution/src/__init__.py
diskpop/diskpop/DiscEvolution/src/chemo_dynamics.py
diskpop/diskpop/DiscEvolution/src/constants.py
diskpop/diskpop/DiscEvolution/src/diffusion.py
diskpop/diskpop/DiscEvolution/src/disc.py
diskpop/diskpop/DiscEvolution/src/disc_utils.py
diskpop/diskpop/DiscEvolution/src/dust.py
diskpop/diskpop/DiscEvolution/src/dust_dynamics.py
diskpop/diskpop/DiscEvolution/src/external_photoev.py
diskpop/diskpop/DiscEvolution/src/grid.py
diskpop/diskpop/DiscEvolution/src/internal_photoev.py
diskpop/diskpop/DiscEvolution/src/mhd_massloss.py
diskpop/diskpop/DiscEvolution/src/opacity.py
diskpop/diskpop/DiscEvolution/src/planet_formation.py
diskpop/diskpop/pmstracks/AUTHORS.rst
diskpop/diskpop/pmstracks/LICENSE
diskpop/diskpop/pmstracks/__init__.py
diskpop/diskpop/pmstracks/setup.py
diskpop/diskpop/pmstracks/pmstracks/__init__.py
diskpop/diskpop/pmstracks/pmstracks/_version.py
diskpop/diskpop/pmstracks/pmstracks/pmstracks.py
diskpop-0.0.12.dist-info/LICENSE
diskpop-0.0.12.dist-info/METADATA
diskpop-0.0.12.dist-info/WHEEL
diskpop-0.0.12.dist-info/top_level.txt
diskpop-0.0.12.dist-info/RECORD
