Metadata-Version: 2.1
Name: diskpop
Version: 0.0.12
Summary: A Python code to perform protoplanetary disc population synthesis
Home-page: https://bitbucket.org/diskpopteam/diskpop/src/master/
Author: Alice Somigliana, Giovanni Rosotti, Marco Tazzari, Leonardo Testi, Giuseppe Lodato, Claudia Toci, Rossella Anania, Benoit Tabone
Author-email: alice.somigliana@eso.org
License: GPL
Platform: UNKNOWN
Classifier: Development Status :: 3 - Alpha
Classifier: Intended Audience :: Developers
Classifier: Intended Audience :: Science/Research
Classifier: Operating System :: OS Independent
Classifier: Programming Language :: Python :: 3
Requires-Dist: numpy (==1.21)
Requires-Dist: pandas
Requires-Dist: matplotlib
Requires-Dist: scipy
Requires-Dist: h5py
